pyramid_orb/__init__.py
pyramid_orb/_version.py
pyramid_orb/action.py
pyramid_orb/api.py
pyramid_orb/service.py
pyramid_orb/utils.py
pyramid_orb/services/__init__.py
pyramid_orb/services/collection.py
pyramid_orb/services/model.py
pyramid_orb-2016.1.5.dist-info/DESCRIPTION.rst
pyramid_orb-2016.1.5.dist-info/METADATA
pyramid_orb-2016.1.5.dist-info/RECORD
pyramid_orb-2016.1.5.dist-info/WHEEL
pyramid_orb-2016.1.5.dist-info/metadata.json
pyramid_orb-2016.1.5.dist-info/top_level.txt
