Metadata-Version: 2.0
Name: pyramid-orb
Version: 2016.1.5
Summary: Bindings for the pyramid webframework and the ORB database ORM library.
Home-page: https://github.com/ProjexSoftware/pyramid_orb
Author: Eric Hulser
Author-email: eric.hulser@gmail.com
License: MIT
Platform: UNKNOWN
Requires-Dist: orb-api
Requires-Dist: projex
Requires-Dist: pyramid
Requires-Dist: pyramid-restful
